openbb_polygon/__init__.py
openbb_polygon/models/__init__.py
openbb_polygon/models/balance_sheet.py
openbb_polygon/models/cash_flow.py
openbb_polygon/models/company_news.py
openbb_polygon/models/crypto_historical.py
openbb_polygon/models/currency_historical.py
openbb_polygon/models/currency_pairs.py
openbb_polygon/models/currency_snapshots.py
openbb_polygon/models/equity_historical.py
openbb_polygon/models/equity_nbbo.py
openbb_polygon/models/income_statement.py
openbb_polygon/models/index_historical.py
openbb_polygon/models/market_snapshots.py
openbb_polygon/py.typed
openbb_polygon/utils/__init__.py
openbb_polygon/utils/helpers.py
openbb_polygon-1.4.1.dist-info/METADATA
openbb_polygon-1.4.1.dist-info/WHEEL
openbb_polygon-1.4.1.dist-info/entry_points.txt
openbb_polygon-1.4.1.dist-info/RECORD
